IUBConfiguration/IUBConfiguration.py
IUBConfiguration/__init__.py
IUBConfiguration-0.0.2.dist-info/LICENSE
IUBConfiguration-0.0.2.dist-info/METADATA
IUBConfiguration-0.0.2.dist-info/WHEEL
IUBConfiguration-0.0.2.dist-info/top_level.txt
IUBConfiguration-0.0.2.dist-info/RECORD
