Metadata-Version: 2.1
Name: IUBConfiguration
Version: 0.0.2
Summary: A small script to read Yaml configuration file
Home-page: https://github.com/Timmy93/IUBConfiguration
Author: Timmy93
Author-email: masomeno2006@hotmail.it
License: UNKNOWN
Project-URL: Bug Tracker, https://github.com/Timmy93/IUBConfiguration/issues
Platform: UNKNOWN
Classifier: Programming Language :: Python :: 3
Classifier: License :: OSI Approved :: MIT License
Classifier: Operating System :: OS Independent
Requires-Python: >=3.6
License-File: LICENSE
